prunarr/__init__.py
prunarr/cli.py
prunarr/config.py
prunarr/logger.py
prunarr/main.py
prunarr/prunarr.py
prunarr/radarr.py
prunarr/sonarr.py
prunarr/tautulli.py
prunarr/api/__init__.py
prunarr/api/base_client.py
prunarr/cache/__init__.py
prunarr/cache/cache_config.py
prunarr/cache/cache_manager.py
prunarr/cache/cache_store.py
prunarr/commands/__init__.py
prunarr/commands/cache.py
prunarr/commands/history.py
prunarr/commands/movies.py
prunarr/commands/providers.py
prunarr/commands/series.py
prunarr/justwatch/__init__.py
prunarr/justwatch/client.py
prunarr/justwatch/exceptions.py
prunarr/justwatch/models.py
prunarr/justwatch/queries.py
prunarr/models/__init__.py
prunarr/models/episode.py
prunarr/models/movie.py
prunarr/models/series.py
prunarr/models/watch_history.py
prunarr/services/__init__.py
prunarr/services/media_matcher.py
prunarr/services/movie_service.py
prunarr/services/series_service.py
prunarr/services/streaming_checker.py
prunarr/services/user_service.py
prunarr/services/watch_calculator.py
prunarr/utils/__init__.py
prunarr/utils/filters.py
prunarr/utils/formatters.py
prunarr/utils/parsers.py
prunarr/utils/serializers.py
prunarr/utils/table_helpers.py
prunarr/utils/tables.py
prunarr/utils/validators.py
prunarr-1.1.0.dist-info/licenses/LICENSE
prunarr-1.1.0.dist-info/METADATA
prunarr-1.1.0.dist-info/WHEEL
prunarr-1.1.0.dist-info/entry_points.txt
prunarr-1.1.0.dist-info/top_level.txt
prunarr-1.1.0.dist-info/RECORD
