Metadata-Version: 2.4
Name: prunarr
Version: 1.1.0
Summary: Automated media library cleanup for Radarr and Sonarr based on Tautulli watch status
Author-email: Haije Ploeg <ploeg.haije@gmail.com>
License: Apache-2.0
Project-URL: Homepage, https://github.com/hploeg/prunarr
Project-URL: Repository, https://github.com/hploeg/prunarr
Project-URL: Documentation, https://github.com/hploeg/prunarr#readme
Project-URL: Bug Reports, https://github.com/hploeg/prunarr/issues
Keywords: radarr,sonarr,tautulli,media,automation,cleanup
Classifier: Development Status :: 5 - Production/Stable
Classifier: Intended Audience :: System Administrators
Classifier: License :: OSI Approved :: Apache Software License
Classifier: Operating System :: OS Independent
Classifier: Programming Language :: Python :: 3
Classifier: Programming Language :: Python :: 3.9
Classifier: Programming Language :: Python :: 3.10
Classifier: Programming Language :: Python :: 3.11
Classifier: Programming Language :: Python :: 3.12
Classifier: Topic :: System :: Systems Administration
Classifier: Topic :: Multimedia
Requires-Python: >=3.9
License-File: LICENSE
Requires-Dist: typer[all]>=0.9.0
Requires-Dist: rich>=13.7.0
Requires-Dist: pydantic>=2.5.0
Requires-Dist: pyyaml>=6.0.1
Requires-Dist: requests>=2.31.0
Requires-Dist: pyarr>=5.2.0
Provides-Extra: dev
Requires-Dist: pytest>=7.4.3; extra == "dev"
Requires-Dist: pytest-cov>=4.1.0; extra == "dev"
Requires-Dist: pytest-mock>=3.12.0; extra == "dev"
Requires-Dist: black>=23.11.0; extra == "dev"
Requires-Dist: isort>=5.12.0; extra == "dev"
Requires-Dist: flake8>=6.1.0; extra == "dev"
Requires-Dist: autoflake>=2.2.0; extra == "dev"
Requires-Dist: mypy>=1.7.1; extra == "dev"
Requires-Dist: bandit>=1.7.5; extra == "dev"
Requires-Dist: safety>=2.3.4; extra == "dev"
Requires-Dist: pre-commit>=3.6.0; extra == "dev"
Dynamic: license-file
